[
    {
        "index": 0,
        "name": "vertiport 1",
        "points": [
            {
                "longitude": 114.16673355381066,
                "latitude": 22.320877279200293,
                "height": 7.039195044897497,
                "cartesian": {
                    "x": -2416685.690942979,
                    "y": 5385730.582598291,
                    "z": 2407322.3823052444
                },
                "neuDistances": {
                    "north": 559.9999839823847,
                    "east": 429.9999999999301,
                    "up": 6.999993425137433
                }
            }
        ]
    },
    {
        "index": 1,
        "name": "vertiport 2",
        "points": [
            {
                "longitude": 114.16479229306063,
                "latitude": 22.31789722269341,
                "height": 7.008307307958603,
                "cartesian": {
                    "x": -2416554.5040261224,
                    "y": 5385926.774579545,
                    "z": 2407017.097685116
                },
                "neuDistances": {
                    "north": 229.9999840582065,
                    "east": 230.0000000012285,
                    "up": 6.9999934567555755
                }
            }
        ]
    },
    {
        "index": 2,
        "name": "vertiport 3",
        "points": [
            {
                "longitude": 114.16518063537791,
                "latitude": 22.323676793758537,
                "height": 7.065354315564036,
                "cartesian": {
                    "x": -2416491.526780348,
                    "y": 5385688.677192726,
                    "z": 2407609.16482719
                },
                "neuDistances": {
                    "north": 869.999983916686,
                    "east": 270.00000000009766,
                    "up": 6.999993398988352
                }
            }
        ]
    },
    {
        "index": 3,
        "name": "vertiport 4",
        "points": [
            {
                "longitude": 114.17517812397023,
                "latitude": 22.32412785316894,
                "height": 7.199115009047091,
                "cartesian": {
                    "x": -2417423.5148913204,
                    "y": 5385249.748253981,
                    "z": 2407655.420072346
                },
                "neuDistances": {
                    "north": 919.9999836110096,
                    "east": 1299.999999998887,
                    "up": 6.9999932737097765
                }
            }
        ]
    },
    {
        "index": 4,
        "name": "vertiport 5",
        "points": [
            {
                "longitude": 114.17488712554461,
                "latitude": 22.326295215627493,
                "height": 7.23241413757205,
                "cartesian": {
                    "x": -2417358.840973762,
                    "y": 5385178.881445298,
                    "z": 2407877.445250594
                },
                "neuDistances": {
                    "north": 1159.999983530524,
                    "east": 1269.9999999997272,
                    "up": 6.99999324065999
                }
            }
        ]
    },
    {
        "index": 5,
        "name": "vertiport 6",
        "points": [
            {
                "longitude": 114.1633364254254,
                "latitude": 22.31997427212634,
                "height": 7.017170433886349,
                "cartesian": {
                    "x": -2416381.8978360095,
                    "y": 5385908.491443541,
                    "z": 2407229.8718143273
                },
                "neuDistances": {
                    "north": 459.9999840335301,
                    "east": 79.999999999729,
                    "up": 6.999993447512026
                }
            }
        ]
    },
    {
        "index": 6,
        "name": "vertiport 7",
        "points": [
            {
                "longitude": 114.16323937499601,
                "latitude": 22.321961002070747,
                "height": 7.036817620508373,
                "cartesian": {
                    "x": -2416338.580197845,
                    "y": 5385836.366981158,
                    "z": 2407433.394894415
                },
                "neuDistances": {
                    "north": 679.9999839848265,
                    "east": 70.00000000045003,
                    "up": 6.999993427254225
                }
            }
        ]
    },
    {
        "index": 7,
        "name": "vertiport 8",
        "points": [
            {
                "longitude": 114.17517798598728,
                "latitude": 22.32259265359845,
                "height": 7.1767417984083295,
                "cartesian": {
                    "x": -2417449.937342461,
                    "y": 5385308.643773834,
                    "z": 2407498.1522377506
                },
                "neuDistances": {
                    "north": 749.9999836656009,
                    "east": 1299.9999999995978,
                    "up": 6.999993295043453
                }
            }
        ]
    },
    {
        "index": 8,
        "name": "vertiport 9",
        "points": [
            {
                "longitude": 114.16644224694353,
                "latitude": 22.316361990775114,
                "height": 7.0128139378502965,
                "cartesian": {
                    "x": -2416736.0324009727,
                    "y": 5385916.084523096,
                    "z": 2406859.829850454
                },
                "neuDistances": {
                    "north": 59.9999840505692,
                    "east": 399.999999999286,
                    "up": 6.99999345432979
                }
            }
        ]
    },
    {
        "index": 9,
        "name": "vertiport 10",
        "points": [
            {
                "longitude": 114.16692753748502,
                "latitude": 22.316452284369344,
                "height": 7.01624646410346,
                "cartesian": {
                    "x": -2416780.097528467,
                    "y": 5385892.153734778,
                    "z": 2406869.080899542
                },
                "neuDistances": {
                    "north": 69.99998404281033,
                    "east": 449.9999999991161,
                    "up": 6.999993449582448
                }
            }
        ]
    }
]